.coveragerc
.gitignore
.travis.yml
LICENSE
Makefile
README.md
pytest.ini
requirements-dev.txt
requirements.txt
setup.py
generator/__init__.py
generator/__main__.py
generator/generator.py
generator/verb_extender.py
oai_sam.egg-info/PKG-INFO
oai_sam.egg-info/SOURCES.txt
oai_sam.egg-info/dependency_links.txt
oai_sam.egg-info/entry_points.txt
oai_sam.egg-info/requires.txt
oai_sam.egg-info/top_level.txt
test/generator_test.py
test/petshop_extended.json
test/verb_extender_test.py