Metadata-Version: 2.1
Name: oai-sam
Version: 0.0.1
Summary: Generate SAM template and AWS OpenAPI extended docs
Home-page: https://github.com/fulder/openapi-to-aws-apigateway
Author: Michal Sadowski
Author-email: misad90@gmail.com
License: UNKNOWN
Platform: UNKNOWN
Classifier: Programming Language :: Python :: 3
Classifier: License :: OSI Approved :: MIT License
Classifier: Operating System :: OS Independent
Requires-Python: >=2.6, >=3.3
